pypdxapi/__init__.py
pypdxapi/__version__.py
pypdxapi/exceptions.py
pypdxapi/module.py
pypdxapi/camera/__init__.py
pypdxapi/camera/camera.py
pypdxapi/camera/hd77.py
pypdxapi/helpers/__init__.py
pypdxapi/helpers/discover.py
tests/__init__.py
tests/camera/__init__.py
tests/camera/test_camera.py
tests/camera/test_hd77.py
tests/helpers/__init__.py
tests/helpers/test_discover.py
pypdxapi-0.1.1.dist-info/LICENSE
pypdxapi-0.1.1.dist-info/METADATA
pypdxapi-0.1.1.dist-info/WHEEL
pypdxapi-0.1.1.dist-info/top_level.txt
pypdxapi-0.1.1.dist-info/RECORD
