Metadata-Version: 2.1
Name: pypdxapi
Version: 0.1.1
Summary: Python package for Paradox Modules
Home-page: https://github.com/hallenmaia/pypdxapi/
Author: Hallen Maia
Author-email: hallenmaia@me.com
License: MIT license
Keywords: api,client,paradox,camera
Platform: UNKNOWN
Classifier: Programming Language :: Python :: 3
Classifier: Programming Language :: Python :: 3.8
Classifier: Programming Language :: Python :: 3.9
Classifier: Natural Language :: English
Classifier: License :: OSI Approved :: MIT License
Classifier: Topic :: Software Development :: Libraries :: Python Modules
Requires-Python: >=3.8
Requires-Dist: aiohttp (==3.6.2)
Requires-Dist: yarl (==1.4.2)
